{"Unknown Tissue":"image_00023_0_.png","cerebral peduncle left":"image_00023_1_.png","optic tract left":"image_00023_2_.png","middle cerebellar peduncle left":"image_00023_3_.png","internal capsule posterior limb left":"image_00023_4_.png","trigeminal nerve left":"image_00023_5_.png","thalamus excluding pulvinar left":"image_00023_6_.png","subthalamic nucleus left":"image_00023_7_.png","substantia nigra right":"image_00023_8_.png","inferior cerebellar peduncle left":"image_00023_9_.png","pulvinar nuclei left":"image_00023_10_.png"}